okcoin/DataMangement.py
okcoin/DataObjects.py
okcoin/__init__.py
okcoin/ticker.py
okcoin_GBRUNNER-0.0.3.dist-info/LICENSE
okcoin_GBRUNNER-0.0.3.dist-info/METADATA
okcoin_GBRUNNER-0.0.3.dist-info/WHEEL
okcoin_GBRUNNER-0.0.3.dist-info/top_level.txt
okcoin_GBRUNNER-0.0.3.dist-info/RECORD
