Metadata-Version: 2.1
Name: okcoin-GBRUNNER
Version: 0.0.3
Summary: A Python package for interfacing with okcoin.
Home-page: https://github.com/gbrunner/python-api-for-okcoin
Author: Gregory Brunner
Author-email: gregory.brunner@protonmail.com
License: UNKNOWN
Project-URL: Bug Tracker, https://github.com/gbrunner/python-api-for-okcoin/issues
Platform: UNKNOWN
Classifier: Programming Language :: Python :: 3
Classifier: License :: OSI Approved :: MIT License
Classifier: Operating System :: OS Independent
Requires-Python: >=3.6
License-File: LICENSE
